web_scraper_toolkit/__init__.py
web_scraper_toolkit/cli.py
web_scraper_toolkit/browser/__init__.py
web_scraper_toolkit/browser/config.py
web_scraper_toolkit/browser/playwright_crawler.py
web_scraper_toolkit/browser/playwright_handler.py
web_scraper_toolkit/browser/solver.py
web_scraper_toolkit/core/__init__.py
web_scraper_toolkit/core/diagnostics.py
web_scraper_toolkit/core/file_utils.py
web_scraper_toolkit/core/http_client.py
web_scraper_toolkit/core/input.py
web_scraper_toolkit/core/logger.py
web_scraper_toolkit/core/user_agents.py
web_scraper_toolkit/core/utils.py
web_scraper_toolkit/core/verify_deps.py
web_scraper_toolkit/core/automation/__init__.py
web_scraper_toolkit/core/automation/forms.py
web_scraper_toolkit/core/automation/retry.py
web_scraper_toolkit/core/automation/utilities.py
web_scraper_toolkit/core/content/__init__.py
web_scraper_toolkit/core/content/chunking.py
web_scraper_toolkit/core/content/tokens.py
web_scraper_toolkit/core/state/__init__.py
web_scraper_toolkit/core/state/cache.py
web_scraper_toolkit/core/state/history.py
web_scraper_toolkit/core/state/session.py
web_scraper_toolkit/crawler/__init__.py
web_scraper_toolkit/crawler/config.py
web_scraper_toolkit/crawler/engine.py
web_scraper_toolkit/crawler/frontier.py
web_scraper_toolkit/crawler/politeness.py
web_scraper_toolkit/crawler/state.py
web_scraper_toolkit/parsers/__init__.py
web_scraper_toolkit/parsers/config.py
web_scraper_toolkit/parsers/content.py
web_scraper_toolkit/parsers/discovery.py
web_scraper_toolkit/parsers/html_to_markdown.py
web_scraper_toolkit/parsers/scraping_tools.py
web_scraper_toolkit/parsers/utils.py
web_scraper_toolkit/parsers/extraction/__init__.py
web_scraper_toolkit/parsers/extraction/contacts.py
web_scraper_toolkit/parsers/extraction/links.py
web_scraper_toolkit/parsers/extraction/media.py
web_scraper_toolkit/parsers/extraction/metadata.py
web_scraper_toolkit/parsers/search/__init__.py
web_scraper_toolkit/parsers/search/search.py
web_scraper_toolkit-0.1.7.dist-info/licenses/LICENSE
web_scraper_toolkit-0.1.7.dist-info/METADATA
web_scraper_toolkit-0.1.7.dist-info/WHEEL
web_scraper_toolkit-0.1.7.dist-info/entry_points.txt
web_scraper_toolkit-0.1.7.dist-info/top_level.txt
web_scraper_toolkit-0.1.7.dist-info/RECORD
