Metadata-Version: 2.4
Name: web-scraper-toolkit
Version: 0.1.7
Summary: A powerful, standalone web scraping toolkit using Playwright and various parsers.
Author: Roy Dawson IV
License-Expression: MIT
Project-URL: Homepage, https://github.com/imyourboyroy/WebScraperToolkit
Project-URL: Repository, https://github.com/imyourboyroy/WebScraperToolkit
Classifier: Programming Language :: Python :: 3
Classifier: Programming Language :: Python :: 3.10
Classifier: Programming Language :: Python :: 3.11
Classifier: Programming Language :: Python :: 3.12
Classifier: Programming Language :: Python :: 3.13
Classifier: Operating System :: OS Independent
Requires-Python: >=3.10
License-File: LICENSE
Requires-Dist: playwright
Requires-Dist: beautifulsoup4
Requires-Dist: requests
Requires-Dist: lxml
Requires-Dist: pypdf
Requires-Dist: rich
Requires-Dist: playwright-stealth>=2.0.0
Requires-Dist: fastmcp
Requires-Dist: emailtoolkit
Requires-Dist: phonenumbers
Requires-Dist: aiohttp
Requires-Dist: aiohttp-socks
Dynamic: license-file
